setup.py
ShareClass/Update_chormedriver.py
ShareClass/__init__.py
ShareClass/add_logo.py
ShareClass/change_img_size.py
ShareClass/exchange_rate.py
ShareClass/ftp_upload.py
ShareClass/google_translate.py
ShareClass/thread_api.py
ShareClass.egg-info/PKG-INFO
ShareClass.egg-info/SOURCES.txt
ShareClass.egg-info/dependency_links.txt
ShareClass.egg-info/requires.txt
ShareClass.egg-info/top_level.txt